LICENSE.txt
README.md
pyproject.toml
src/hikepy/__init__.py
src/hikepy/app.py
src/hikepy/business.py
src/hikepy/command.py
src/hikepy/config.py
src/hikepy/hklogger.py
src/hikepy/model.py
src/hikepy/tools.py
src/hikepy.egg-info/PKG-INFO
src/hikepy.egg-info/SOURCES.txt
src/hikepy.egg-info/dependency_links.txt
src/hikepy.egg-info/requires.txt
src/hikepy.egg-info/top_level.txt