Metadata-Version: 2.2
Name: hikepy
Version: 1.0.7
Summary: hikesoft python framework power by wantao
Author-email: wantao <hnck2000@126.com>
Maintainer-email: wantao <hnck2000@126.com>
License: Copyright (c) 2016 The Python Packaging Authority (PyPA)
Project-URL: Homepage, https://github.com/pypa/sampleproject
Project-URL: Bug Reports, https://github.com/pypa/sampleproject/issues
Project-URL: Funding, https://donate.pypi.org
Project-URL: Say Thanks!, http://saythanks.io/to/example
Project-URL: Source, https://github.com/pypa/sampleproject/
Keywords: hikepy,framework,setuptools,development
Classifier: Development Status :: 3 - Alpha
Classifier: Intended Audience :: Developers
Classifier: Topic :: Software Development :: Build Tools
Classifier: License :: OSI Approved :: MIT License
Classifier: Programming Language :: Python :: 3
Classifier: Programming Language :: Python :: 3.8
Classifier: Programming Language :: Python :: 3.9
Classifier: Programming Language :: Python :: 3.10
Classifier: Programming Language :: Python :: 3.11
Classifier: Programming Language :: Python :: 3.12
Classifier: Programming Language :: Python :: 3 :: Only
Requires-Python: >=3.8
License-File: LICENSE.txt
Requires-Dist: fastapi[all]
Requires-Dist: uvicorn[standard]
Requires-Dist: redis
Requires-Dist: pyjwt
Requires-Dist: passlib[bcrypt]
Requires-Dist: pyyaml
Requires-Dist: sqlalchemy
Requires-Dist: aiomysql
Requires-Dist: motor
